pathml/__init__.py
pathml/_logging.py
pathml/_version.py
pathml/utils.py
pathml/core/__init__.py
pathml/core/h5managers.py
pathml/core/masks.py
pathml/core/slide_backends.py
pathml/core/slide_data.py
pathml/core/slide_dataset.py
pathml/core/slide_types.py
pathml/core/tile.py
pathml/core/tiles.py
pathml/core/utils.py
pathml/datasets/__init__.py
pathml/datasets/base_data_module.py
pathml/datasets/datasets.py
pathml/datasets/deepfocus.py
pathml/datasets/pannuke.py
pathml/datasets/utils.py
pathml/graph/__init__.py
pathml/graph/preprocessing.py
pathml/graph/utils.py
pathml/inference/__init__.py
pathml/inference/inference.py
pathml/inference/mesmer_utils.py
pathml/ml/__init__.py
pathml/ml/dataset.py
pathml/ml/hovernet.py
pathml/ml/layers.py
pathml/ml/utils.py
pathml/ml/models/__init__.py
pathml/ml/models/hactnet.py
pathml/ml/models/hovernet.py
pathml/preprocessing/__init__.py
pathml/preprocessing/pipeline.py
pathml/preprocessing/tilestitcher.py
pathml/preprocessing/tiling.py
pathml/preprocessing/transforms.py
pathml/preprocessing/workflows.py
pathml-3.0.4.dist-info/licenses/LICENSE
pathml-3.0.4.dist-info/METADATA
pathml-3.0.4.dist-info/WHEEL
pathml-3.0.4.dist-info/dependency_links.txt
pathml-3.0.4.dist-info/top_level.txt
pathml-3.0.4.dist-info/RECORD
