Metadata-Version: 2.4
Name: pathml
Version: 3.0.4
Summary: Tools for computational pathology
Author: Jacob Rosenthal, Ryan Carelli et al.
Author-email: PathML@dfci.harvard.edu
Project-URL: Documentation, https://pathml.readthedocs.io/en/stable
Project-URL: Source Code, https://github.com/Dana-Farber-AIOS/pathml
Classifier: License :: OSI Approved :: GNU General Public License v2 (GPLv2)
Classifier: Programming Language :: Python :: 3
Classifier: Programming Language :: Python :: 3.8
Classifier: Operating System :: OS Independent
Classifier: Development Status :: 4 - Beta
Classifier: Intended Audience :: Science/Research
Classifier: Framework :: Sphinx
Classifier: Framework :: Pytest
Classifier: Topic :: Scientific/Engineering :: Artificial Intelligence
Classifier: Topic :: Scientific/Engineering :: Bio-Informatics
Classifier: Topic :: Scientific/Engineering :: Image Processing
Classifier: Topic :: Scientific/Engineering :: Image Recognition
Classifier: Topic :: Scientific/Engineering :: Medical Science Apps.
Classifier: Topic :: Software Development :: Libraries :: Python Modules
License-File: LICENSE
Requires-Dist: numpy==1.23.5
Requires-Dist: pandas<=2.1.4
Requires-Dist: scipy<=1.11.4
Requires-Dist: scikit-image<=0.22.0
Requires-Dist: statsmodels
Requires-Dist: matplotlib<=3.8.2
Requires-Dist: openslide-python==1.3.1
Requires-Dist: pydicom==2.4.4
Requires-Dist: h5py==3.10.0
Requires-Dist: scikit-learn
Requires-Dist: dask[distributed]
Requires-Dist: anndata>=0.7.6
Requires-Dist: scanpy==1.9.6
Requires-Dist: torch==2.8.0
Requires-Dist: opencv-contrib-python==4.8.1.78
Requires-Dist: python-bioformats==4.0.7
Requires-Dist: python-javabridge==4.0.3
Requires-Dist: loguru==0.7.2
Requires-Dist: networkx<=3.2.1
Requires-Dist: torch-geometric==2.3.1
Requires-Dist: onnx==1.17.0
Requires-Dist: onnxruntime==1.16.3
Requires-Dist: jpype1==1.4.1
Requires-Dist: tqdm==4.66.3
Requires-Dist: anndata<=0.10.3
Requires-Dist: pydicom==2.4.4
Dynamic: author
Dynamic: author-email
Dynamic: classifier
Dynamic: description
Dynamic: description-content-type
Dynamic: license-file
Dynamic: project-url
Dynamic: requires-dist
Dynamic: summary
